async_mediawiki/__init__.py
async_mediawiki/exceptions.py
async_mediawiki/http.py
async_mediawiki/page.py
async_mediawiki/wiki.py
async_mediawiki-0.2.0.dist-info/METADATA
async_mediawiki-0.2.0.dist-info/RECORD
async_mediawiki-0.2.0.dist-info/WHEEL
async_mediawiki-0.2.0.dist-info/top_level.txt
