Metadata-Version: 2.1
Name: async-mediawiki
Version: 0.2.0
Summary: Async Mediawiki Python library
Home-page: https://github.com/Gelbpunkt/async-mediawiki
Author: Jens Reidel
Author-email: jens.reidel@gmail.com
License: MIT
Platform: UNKNOWN
Classifier: Programming Language :: Python :: 3
Classifier: License :: OSI Approved :: MIT License
Classifier: Operating System :: OS Independent
Requires-Dist: aiohttp (<3.4.0,>=3.3.0)
